judgy/__init__.py
judgy/core.py
judgy/plotting.py
judgy/synthetic.py
judgy-0.1.0.dist-info/licenses/LICENSE
judgy-0.1.0.dist-info/METADATA
judgy-0.1.0.dist-info/WHEEL
judgy-0.1.0.dist-info/top_level.txt
judgy-0.1.0.dist-info/RECORD
