Metadata-Version: 2.4
Name: judgy
Version: 0.1.0
Summary: A Python library for estimating success rates when using LLM judges for evaluation
Author-email: Shreya Shankar <ss.shankar505@gmail.com>
License: MIT
Project-URL: Homepage, https://github.com/ai-evals-course/judgy
Project-URL: Repository, https://github.com/ai-evals-course/judgy
Project-URL: Documentation, https://github.com/ai-evals-course/judgy#readme
Project-URL: Bug Tracker, https://github.com/ai-evals-course/judgy/issues
Keywords: llm,judge,evaluation,machine-learning,nlp
Classifier: Development Status :: 4 - Beta
Classifier: Intended Audience :: Developers
Classifier: Intended Audience :: Science/Research
Classifier: License :: OSI Approved :: MIT License
Classifier: Operating System :: OS Independent
Classifier: Programming Language :: Python :: 3
Classifier: Programming Language :: Python :: 3.8
Classifier: Programming Language :: Python :: 3.9
Classifier: Programming Language :: Python :: 3.10
Classifier: Programming Language :: Python :: 3.11
Classifier: Programming Language :: Python :: 3.12
Classifier: Topic :: Scientific/Engineering
Classifier: Topic :: Software Development :: Libraries :: Python Modules
Requires-Python: >=3.8
License-File: LICENSE
Requires-Dist: numpy>=1.20.0
Provides-Extra: plotting
Requires-Dist: matplotlib>=3.5.0; extra == "plotting"
Provides-Extra: dev
Requires-Dist: pytest>=7.0.0; extra == "dev"
Requires-Dist: pytest-cov>=4.0.0; extra == "dev"
Requires-Dist: black>=22.0.0; extra == "dev"
Requires-Dist: isort>=5.10.0; extra == "dev"
Requires-Dist: flake8>=5.0.0; extra == "dev"
Requires-Dist: mypy>=1.0.0; extra == "dev"
Dynamic: license-file
